colored_logs/__init__.py
colored_logs/logger.py
colored_logs/utils.py
colored_logs/models/__init__.py
colored_logs/models/animation_type.py
colored_logs/models/color.py
colored_logs/models/color_config.py
colored_logs/models/color_pair.py
colored_logs/models/icon_set.py
colored_logs/models/log_environment.py
colored_logs/models/log_info.py
colored_logs/models/log_type.py
colored_logs-0.2.10.dist-info/LICENSE
colored_logs-0.2.10.dist-info/METADATA
colored_logs-0.2.10.dist-info/WHEEL
colored_logs-0.2.10.dist-info/top_level.txt
colored_logs-0.2.10.dist-info/RECORD
