Metadata-Version: 2.1
Name: colored_logs
Version: 0.2.10
Summary: A colored logs package based on 'colored'
Home-page: https://github.com/kkristof200/ColoredLogs
Author: Kovacs Kristof-Attila
License: UNKNOWN
Platform: UNKNOWN
Classifier: Programming Language :: Python :: 3
Classifier: License :: OSI Approved :: MIT License
Classifier: Operating System :: OS Independent
Requires-Python: >=3.5
